lotr_movie_sdk/__init__.py
lotr_movie_sdk/movie.py
lotr_movie_sdk-0.1.1.dist-info/LICENSE
lotr_movie_sdk-0.1.1.dist-info/WHEEL
lotr_movie_sdk-0.1.1.dist-info/METADATA
lotr_movie_sdk-0.1.1.dist-info/RECORD
