Metadata-Version: 2.1
Name: lotr-movie-sdk
Version: 0.1.1
Summary: Lord Of TheRings Movie SDK - Test for LibLab
Home-page: https://github.com/sciffer/lotr-movie-sdk
License: MIT
Author: sciffer
Author-email: shaly.c@gmail.com
Requires-Python: >=3.9,<4.0
Classifier: Development Status :: 3 - Alpha
Classifier: Intended Audience :: Developers
Classifier: License :: OSI Approved :: MIT License
Classifier: Operating System :: OS Independent
Classifier: Programming Language :: Python :: 3
Classifier: Programming Language :: Python :: 3.9
Classifier: Programming Language :: Python :: 3.10
Classifier: Programming Language :: Python :: 3.11
Classifier: Programming Language :: Python :: 3
Classifier: Programming Language :: Python :: 3.9
Classifier: Topic :: Software Development :: Libraries :: Python Modules
Provides-Extra: docs
Requires-Dist: Sphinx (==4.2.0) ; extra == "docs"
Requires-Dist: requests (>=2.28.2,<3.0.0)
Requires-Dist: sphinx-rtd-theme (==1.0.0) ; extra == "docs"
Requires-Dist: sphinxcontrib-napoleon (==0.7) ; extra == "docs"
Project-URL: Repository, https://github.com/sciffer/lotr-movie-sdk
